sparklines/__init__.py
sparklines/__main__.py
sparklines/sparklines.py
sparklines-0.6.0.dist-info/METADATA
sparklines-0.6.0.dist-info/WHEEL
sparklines-0.6.0.dist-info/entry_points.txt
sparklines-0.6.0.dist-info/licenses/LICENSE.txt
sparklines-0.6.0.dist-info/RECORD
