Metadata-Version: 2.4
Name: sparklines
Version: 0.6.0
Summary: Generate sparklines for numbers using Unicode characters only.
Project-URL: Homepage, https://github.com/deeplook/sparklines
Project-URL: Issues, https://github.com/deeplook/sparklines/issues
Project-URL: CI, https://github.com/deeplook/sparklines/actions
Project-URL: Changelog, https://github.com/deeplook/sparklines/releases
Project-URL: Repository, https://github.com/deeplook/sparklines.git
Project-URL: Documentation, https://github.com/deeplook/sparklines
Author-email: Dinu Gherman <gherman@darwin.in-berlin.de>
License-Expression: GPL-3.0-or-later
License-File: LICENSE.txt
Keywords: chart,tool,visualization
Classifier: Development Status :: 5 - Production/Stable
Classifier: Environment :: Console
Classifier: Intended Audience :: Developers
Classifier: Intended Audience :: End Users/Desktop
Classifier: Intended Audience :: Other Audience
Classifier: License :: OSI Approved :: GNU General Public License v3 or later (GPLv3+)
Classifier: Programming Language :: Python :: 3
Classifier: Programming Language :: Python :: 3.9
Classifier: Programming Language :: Python :: 3.10
Classifier: Programming Language :: Python :: 3.11
Classifier: Programming Language :: Python :: 3.12
Classifier: Programming Language :: Python :: 3.13
Classifier: Programming Language :: Python :: Implementation :: PyPy
Requires-Python: >=3.9
Requires-Dist: termcolor>=2.4.0
Provides-Extra: test
Requires-Dist: pytest>=7.0.0; extra == 'test'
Requires-Dist: tomli>=2.0.0; (python_version < '3.11') and extra == 'test'
